{
  "Id": "warrior",
  "Name": "Warrior",
  "Description": "Master of armor and sword.",
  "Hitpoints": "300+level*7",
  "Mana": "150+level*3",
  "Moves": "150+level",
  "StartingEquipment": [
    "greenLantern",
    "cloakOfRookie",
    "ironSword",
    "ironHelmet",
    "ironArmor",
    "ironGloves",
    "ironGreaves",
    "ironBoots",
    "ironShield"
  ],
  "StartingSkills": [
    "melee",
    "strength",
    "constitution"
  ],
  "StartingInventory": [
    {
      "Item": "novicePotionOfHealing",
      "Quantity": 5
    },
    {
      "Item": "novicePotionOfMana",
      "Quantity": 5
    },
    {
      "Item": "novicePotionOfMoves",
      "Quantity": 5
    }
  ],
  "StartingGold": 2000,
  "StartingSkillPoints": 1,
  "PrimeModifiers": {
    "Armor": 10,
    "WeaponDamage": 2
  }
}