{
  "Id": "martialArts",
  "Name": "Martial Arts",
  "Class": "monk",
  "Levels": [
    {
      "Modifiers": {
        "MartialArtsMinimumDamage": 2,
        "MartialArtsMaximumDamage": 10,
        "MartialArtsAttacksCount": 1,
        "MartialArtsAttackBonus": 10
      },
      "Abilities": [
        "kick",
        "martialArtsMastery"
      ]
    },
    {
      "Modifiers": {
        "DamageReduction": 1,
        "MartialArtsAttackBonus": 10
      }
    },
    {
      "Modifiers": {
        "MartialArtsMinimumDamage": 2,
        "MartialArtsMaximumDamage": 14,
        "MartialArtsAttacksCount": 1,
        "DamageReduction": 1,
        "MartialArtsAttackBonus": 10
      }
    },
    {
      "Modifiers": {
        "DamageReduction": 1,
        "MartialArtsAttackBonus": 10
      }
    },
    {
      "Modifiers": {
        "MartialArtsMinimumDamage": 3,
        "MartialArtsMaximumDamage": 18,
        "MartialArtsAttacksCount": 1,
        "DamageReduction": 1,
        "MartialArtsAttackBonus": 10
      }
    }
  ],
  "Cost": 2
}